{
	"animations": [
		{
			"offsets": [
				50,
				10
			],
			"indices": [],
			"fps": 24,
			"anim": "singLEFT",
			"loop": false,
			"name": "LORDX_left"
		},
		{
			"offsets": [
				-6,
				24
			],
			"indices": [],
			"fps": 24,
			"anim": "singUP",
			"loop": false,
			"name": "LORDX_up"
		},
		{
			"offsets": [
				-51,
				-13
			],
			"indices": [],
			"fps": 24,
			"anim": "singRIGHT",
			"loop": false,
			"name": "LORDX_right"
		},
		{
			"offsets": [
				-3,
				-94
			],
			"indices": [],
			"fps": 24,
			"anim": "singDOWN",
			"loop": false,
			"name": "LORDX_down"
		},
		{
			"offsets": [
				0,
				0
			],
			"indices": [],
			"fps": 24,
			"anim": "idle",
			"loop": false,
			"name": "LORDX_idle"
		}
	],
	"no_antialiasing": false,
	"image": "characters/LordSex/LORDX_SLAYBALLS",
	"position": [
		0,
		0
	],
	"healthicon": "soylent",
	"flip_x": false,
	"healthbar_colors": [
		120,
		119,
		176
	],
	"camera_position": [
		0,
		0
	],
	"sing_duration": 6.1,
	"scale": 1.3
}